MANIFEST.in
README.md
setup.cfg
setup.py
hctsa/MakeFile
hctsa/__init__.py
hctsa/app.py
hctsa.egg-info/PKG-INFO
hctsa.egg-info/SOURCES.txt
hctsa.egg-info/dependency_links.txt
hctsa.egg-info/top_level.txt
hctsa/descriptive/__init__.py
hctsa/descriptive/multivariat.py
hctsa/descriptive/univariate.py
hctsa/exceptions/__init__.py
hctsa/pipeline/__init__.py
hctsa/pipeline/method_rules.yml
hctsa/pipeline/methods.py
hctsa/pipeline/pipeline.py
hctsa/preparation/__init__.py
hctsa/preparation/cleaning.py
hctsa/preparation/downsampling.py
hctsa/preparation/multivariat.py
hctsa/preparation/normalization.py
hctsa/preparation/transformation.py
hctsa/visualization/__init__.py
hctsa/visualization/seaborn.py